<annotation><filename>048.jpg</filename><folder>users/finalyXL//web_btn_images</folder><source><submittedBy>finalyXL</submittedBy></source><imagesize><nrows>1024</nrows><ncols>1279</ncols></imagesize><object><name>border</name><deleted>0</deleted><verified>0</verified><occluded>no</occluded><attributes>train,</attributes><parts><hasparts/><ispartof/></parts><date>12-Jan-2016 09:29:25</date><id>0</id><polygon><username>finalyXL</username><pt><x>0</x><y>1</y></pt><pt><x>2</x><y>104</y></pt><pt><x>1266</x><y>104</y></pt><pt><x>1270</x><y>0</y></pt></polygon></object><object><name>button</name><deleted>0</deleted><verified>0</verified><occluded>no</occluded><attributes>train,existed,</attributes><parts><hasparts/><ispartof/></parts><date>12-Jan-2016 09:29:45</date><id>1</id><polygon><username>finalyXL</username><pt><x>928</x><y>34</y></pt><pt><x>927</x><y>63</y></pt><pt><x>1030</x><y>62</y></pt><pt><x>1025</x><y>34</y></pt></polygon></object><object><name>button</name><deleted>0</deleted><verified>0</verified><occluded>no</occluded><attributes>train,learn_btn,xt7,yt2</attributes><parts><hasparts/><ispartof/></parts><date>12-Jan-2016 09:30:07</date><id>2</id><polygon><username>finalyXL</username><pt><x>1046</x><y>26</y></pt><pt><x>1044</x><y>68</y></pt><pt><x>1123</x><y>71</y></pt><pt><x>1121</x><y>29</y></pt></polygon></object><object><name>bgi</name><deleted>0</deleted><verified>0</verified><occluded>no</occluded><attributes>train,</attributes><parts><hasparts/><ispartof/></parts><date>12-Jan-2016 09:30:28</date><id>3</id><polygon><username>finalyXL</username><pt><x>6</x><y>156</y></pt><pt><x>2</x><y>594</y></pt><pt><x>1260</x><y>595</y></pt><pt><x>1253</x><y>151</y></pt></polygon></object><object><name>text</name><deleted>0</deleted><verified>0</verified><occluded>no</occluded><attributes>train,</attributes><parts><hasparts/><ispartof/></parts><date>12-Jan-2016 09:30:44</date><id>4</id><polygon><username>finalyXL</username><pt><x>151</x><y>375</y></pt><pt><x>150</x><y>431</y></pt><pt><x>755</x><y>430</y></pt><pt><x>750</x><y>375</y></pt></polygon></object><object><name>button</name><deleted>0</deleted><verified>0</verified><occluded>no</occluded><attributes>train,learn_btn,xt1,yt8</attributes><parts><hasparts/><ispartof/></parts><date>12-Jan-2016 09:31:17</date><id>5</id><polygon><username>finalyXL</username><pt><x>165</x><y>474</y></pt><pt><x>165</x><y>520</y></pt><pt><x>419</x><y>519</y></pt><pt><x>418</x><y>474</y></pt></polygon></object><object><name>border</name><deleted>0</deleted><verified>0</verified><occluded>no</occluded><attributes>train,</attributes><parts><hasparts></hasparts><ispartof></ispartof></parts><date>12-Jan-2016 11:27:10</date><id>6</id><polygon><username>finalyXL</username><pt><x>6</x><y>600</y></pt><pt><x>4</x><y>1022</y></pt><pt><x>1272</x><y>1019</y></pt><pt><x>1267</x><y>604</y></pt></polygon></object></annotation>